llama_index/sparse_embeddings/fastembed/__init__.py
llama_index/sparse_embeddings/fastembed/base.py
llama_index_sparse_embeddings_fastembed-0.3.1.dist-info/METADATA
llama_index_sparse_embeddings_fastembed-0.3.1.dist-info/WHEEL
llama_index_sparse_embeddings_fastembed-0.3.1.dist-info/licenses/LICENSE
llama_index_sparse_embeddings_fastembed-0.3.1.dist-info/RECORD
