Metadata-Version: 2.4
Name: llama-index-sparse-embeddings-fastembed
Version: 0.3.1
Summary: llama-index sparse embeddings fastembed integration
Author-email: Your Name <you@example.com>
License-Expression: MIT
License-File: LICENSE
Requires-Python: <3.13,>=3.9
Requires-Dist: fastembed>=0.2.2
Requires-Dist: llama-index-core<0.15,>=0.13.0
